grabit/__init__.py
grabit/analyse.py
grabit/default.grabit
grabit/grabit.py
grabit/initialisation.py
grabit/models.py
grabit/present.py
grabit/tree.py
grabit/utils.py
grabit-1.8.2.dist-info/entry_points.txt
grabit-1.8.2.dist-info/LICENSE
grabit-1.8.2.dist-info/METADATA
grabit-1.8.2.dist-info/WHEEL
grabit-1.8.2.dist-info/RECORD
