Metadata-Version: 2.1
Name: grabit
Version: 1.8.2
Summary: Simple Python CLI tool for turning directories into a single text file for input to LLMs.
Home-page: https://github.com/Connor56/grabit
Author: Connor Skelland
Author-email: 34070858+Connor56@users.noreply.github.com
Requires-Python: >=3.10,<4.0
Classifier: Programming Language :: Python :: 3
Classifier: Programming Language :: Python :: 3.10
Classifier: Programming Language :: Python :: 3.11
Classifier: Programming Language :: Python :: 3.12
Project-URL: Repository, https://github.com/Connor56/grabit
